EdrParser_.cpython-314-x86_64-linux-gnu.so
TprParser_.cpython-314-x86_64-linux-gnu.so
TprParser/EdrReader.py
TprParser/TprMakeTop.py
TprParser/TprReader.py
TprParser/__init__.py
TprParser/version.py
tprparser-0.1.65.dist-info/METADATA
tprparser-0.1.65.dist-info/WHEEL
tprparser-0.1.65.dist-info/top_level.txt
tprparser-0.1.65.dist-info/RECORD
tprparser-0.1.65.dist-info/licenses/LICENSE
